LICENSE.txt
MANIFEST.in
README.md
setup.py
parsnip/__init__.py
parsnip/__init__.pyc
parsnip/exceptions.py
parsnip/exceptions.pyc
parsnip/tests.py
parsnip/utils.py
parsnip/utils.pyc
parsnip/operators/__init__.py
parsnip/operators/__init__.pyc
parsnip/operators/meteor.py
parsnip/operators/meteor.pyc
parsnip/operators/o2.py
parsnip/operators/o2.pyc
parsnip/operators/three.py
parsnip/operators/three.pyc
parsnip/operators/vodafone.py
parsnip/operators/vodafone.pyc
python_parsnip.egg-info/PKG-INFO
python_parsnip.egg-info/SOURCES.txt
python_parsnip.egg-info/dependency_links.txt
python_parsnip.egg-info/requires.txt
python_parsnip.egg-info/top_level.txt