Metadata-Version: 1.0
Name: python-parsnip
Version: 0.0.1
Summary: Parsnip is a basic python interface to allow the sending of web texts via the main 4 Irish mobile operators websites. It is influenced by/based on Cabbage http://cabbagetexter.com/.
Home-page: https://github.com/timmyomahony/python-parsnip
Author: Timmy O'Mahony
Author-email: me@timmyomahony.com
License: UNKNOWN
Platform: UNKNOWN
